diskurs/__init__.py
diskurs/agent.py
diskurs/assets/can_finalize_system_template.jinja2
diskurs/assets/can_finalize_user_template.jinja2
diskurs/assets/conductor_system_template.jinja2
diskurs/assets/conductor_user_template.jinja2
diskurs/assets/json_formatting.jinja2
diskurs/assets/llm_compiler_planning_system_template.jinja2
diskurs/assets/llm_compiler_planning_user_template.jinja2
diskurs/azure_llm_client.py
diskurs/cli.py
diskurs/conductor_agent.py
diskurs/config.py
diskurs/dispatcher.py
diskurs/entities.py
diskurs/errors.py
diskurs/filesystem_conversation_store.py
diskurs/forum.py
diskurs/heuristic_agent.py
diskurs/immutable_conversation.py
diskurs/llm_client.py
diskurs/llm_compiler/__init__.py
diskurs/llm_compiler/dependency_analyzer.py
diskurs/llm_compiler/entities.py
diskurs/llm_compiler/llm_compiler_agent.py
diskurs/llm_compiler/parallel_executor.py
diskurs/llm_compiler/prompts.py
diskurs/logger_setup.py
diskurs/multistep_agent.py
diskurs/prompt.py
diskurs/protocols.py
diskurs/registry.py
diskurs/telemetry.py
diskurs/tools.py
diskurs/utils.py
diskurs-0.0.79.dist-info/LICENSE
diskurs-0.0.79.dist-info/METADATA
diskurs-0.0.79.dist-info/WHEEL
diskurs-0.0.79.dist-info/entry_points.txt
diskurs-0.0.79.dist-info/RECORD
