Metadata-Version: 2.3
Name: diskurs
Version: 0.0.79
Summary: A hackable and extendable framework for developing LLM-based multi-agentic systems.
License: MIT
Author: Flurin Gishamer
Author-email: fgishamer@me.com
Requires-Python: >=3.12,<4.0
Classifier: License :: OSI Approved :: MIT License
Classifier: Operating System :: OS Independent
Classifier: Programming Language :: Python :: 3
Classifier: Programming Language :: Python :: 3.12
Classifier: Programming Language :: Python :: 3.13
Provides-Extra: azure
Requires-Dist: Jinja2 (>=3.1.6)
Requires-Dist: aiofiles (>=24.1.0,<25.0.0)
Requires-Dist: asyncer (>=0.0.7,<0.0.8)
Requires-Dist: azure-identity[azure] (>=1.19.0,<2.0.0) ; extra == "azure"
Requires-Dist: click (>=8.1.7,<9.0.0)
Requires-Dist: inquirer (>=3.4.0,<4.0.0)
Requires-Dist: networkx (>=3.4.2,<4.0.0)
Requires-Dist: openai (>=1.76.0)
Requires-Dist: pyaml (>=24.7.0,<25.0.0)
Requires-Dist: python-dotenv (>=1.0.1,<2.0.0)
Requires-Dist: tiktoken (>=0.9.0,<0.10.0)
Project-URL: Documentation, https://diskurs.readthedocs.io
Project-URL: Homepage, https://github.com/agentic-diskurs/diskurs
Project-URL: Issues, https://github.com/agentic-diskurs/diskurs/issues
